[
  {
    "id": "6d95fal7c7e40bea",
    "username": "dpmods",
    "password": "dpmods",
    "expiresAt": "2025-12-31",
    "allowOffline": true
  },
  {
    "id": "486e4cc454a07cc6",
    "username": "My",
    "password": "My",
    "expiresAt": "2026-04-20",
    "allowOffline": false
  },
  {
    "id": "android_device_id_2",
    "username": "user2",
    "password": "pass2",
    "expiresAt": "2026-04-20",
    "allowOffline": false
  },
  {
    "id": "android_device_id_2",
    "username": "user2",
    "password": "pass2",
    "expiresAt": "2026-04-20",
    "allowOffline": false
  },
  {
    "id": "android_device_id_2",
    "username": "user2",
    "password": "pass2",
    "expiresAt": "2026-04-20",
    "allowOffline": false
  },
  {
    "id": "android_device_id_2",
    "username": "user2",
    "password": "pass2",
    "expiresAt": "2026-04-20",
    "allowOffline": false
  },
  {
    "id": "android_device_id_2",
    "username": "user2",
    "password": "pass2",
    "expiresAt": "2026-04-20",
    "allowOffline": false
  },
  {
    "id": "android_device_id_2",
    "username": "user2",
    "password": "pass2",
    "expiresAt": "2026-04-20",
    "allowOffline": false
  },
  {
    "id": "android_device_id_2",
    "username": "user2",
    "password": "pass2",
    "expiresAt": "2026-04-20",
    "allowOffline": false
  },
  {
    "id": "android_device_id_2",
    "username": "user2",
    "password": "pass2",
    "expiresAt": "2026-04-20",
    "allowOffline": false
  }
]
